wtool_utils
