Metadata-Version: 2.1
Name: wtool-utils
Version: 1.1
Summary: helper for the wtool app
Home-page: https://github.com/nbdy/wtool_utils
Author: Pascal Eberlein
Author-email: pascal@eberlein.io
License: UNKNOWN
Keywords: companion script wtool utils
Platform: UNKNOWN
Classifier: Intended Audience :: Developers
Classifier: License :: OSI Approved :: MIT License
